Workbook

Sheet README
B1: Bank statement to budget: cleaned rebuild
B2: Cleaned file: real names, figures and records replaced with synthetic data of the same structure.
B4: The original job
B6: An accountancy team needed to budget from a client's business current account, but the only record was five monthly paper statements: 13 scanned pages covering 21 May to 11 October 2022. There was no export and no automation. I transcribed all 183 transactions into Excel, gave every statement period a running balance and a total, and reconciled each period to the closing balance printed on the statement.
B7: This file
B9: Synthetic transactions in the same five period structure (183 rows, same mix of card payments, transfers, bill payments, direct credits and bank charges). The category and budget tabs show how the structured data was used to budget, rebuilt with formulas so any figure can be traced to its rows.
B10: Tabs
B12: • Transactions: one row per transaction. Running balance, statement period and category are formulas.
B13: • Reconciliation: each period's opening balance, money out, money in and computed closing balance, checked against the closing balance typed from the statement. Every period must read Reconciled.
B14: • Category Rules: keyword to category rules. The category formula searches each description for every keyword and takes the matching category, so a new rule recategorises the whole ledger at once.
B15: • Budget: spend by category and period with SUMIFS, the monthly average, a proposed monthly budget (input), and the variance for the period chosen in the selector.
B16: • Checks: transaction count, uncategorised rows, reconciliation status and a tie out between the ledger and the budget totals.
... B19: Yellow cells with blue text are inputs: the opening balance, the statement closing balances, the rules and the proposed budgets. Everything else is calculated.

Sheet Budget
A1: Budget by category
A2: Actuals from the transactions. Proposed budget is an input; variance follows the period selector.
A4: Selected period | B4: P4
A6: Category | B6: P1 | C6: P2 | D6: P3 | E6: P4 | F6: P5 | G6: Total | H6: Monthly average | I6: Share of spend | J6: Proposed monthly budget | K6: Selected period actual | L6: Variance vs budget | M6: Rank
A7: Spending
A8: Transfers out | B8: =SUMIFS(Transactions!$D$6:$D$188,Transactions!$G$6:$G$188,$A8,Transactions!$A$6:$A$188,"P1") -> 575 | C8: =SUMIFS(Transactions!$D$6:$D$188,Transactions!$G$6:$G$188,$A8,Transactions!$A$6:$A$188,"P2") -> 1300 | D8: =SUMIFS(Transactions!$D$6:$D$188,Transactions!$G$6:$G$188,$A8,Transactions!$A$6:$A$188,"P3") -> 1325 | E8: =SUMIFS(Transactions!$D$6:$D$188,Transactions!$G$6:$G$188,$A8,Transactions!$A$6:$A$188,"P4") -> 2550 | F8: =SUMIFS(Transactions!$D$6:$D$188,Transactions!$G$6:$G$188,$A8,Transactions!$A$6:$A$188,"P5") -> 100 | G8: =SUM(B8:F8) -> 5850 | H8: =AVERAGE(B8:E8) -> 1437.5 | I8: =IF($G$20=0,0,G8/$G$20) -> 0.44990414 | J8: 1440 | K8: =INDEX(B8:F8,MATCH($B$4,$B$6:$F$6,0)) -> 2550 | L8: =J8-K8 -> -1110 | M8: =RANK(G8,$G$8:$G$19) -> 1
A9: Supplier payments | B9: =SUMIFS(Transactions!$D$6:$D$188,Transactions!$G$6:$G$188,$A9,Transactions!$A$6:$A$188,"P1") -> 0 | C9: =SUMIFS(Transactions!$D$6:$D$188,Transactions!$G$6:$G$188,$A9,Transactions!$A$6:$A$188,"P2") -> 275 | D9: =SUMIFS(Transactions!$D$6:$D$188,Transactions!$G$6:$G$188,$A9,Transactions!$A$6:$A$188,"P3") -> 1000 | E9: =SUMIFS(Transactions!$D$6:$D$188,Transactions!$G$6:$G$188,$A9,Transactions!$A$6:$A$188,"P4") -> 200 | F9: =SUMIFS(Transactions!$D$6:$D$188,Transactions!$G$6:$G$188,$A9,Transactions!$A$6:$A$188,"P5") -> 0 | G9: =SUM(B9:F9) -> 1475 | H9: =AVERAGE(B9:E9) -> 368.75 | I9: =IF($G$20=0,0,G9/$G$20) -> 0.11343737 | J9: 370 | K9: =INDEX(B9:F9,MATCH($B$4,$B$6:$F$6,0)) -> 200 | L9: =J9-K9 -> 170 | M9: =RANK(G9,$G$8:$G$19) -> 4
A10: Fuel and vehicle | B10: =SUMIFS(Transactions!$D$6:$D$188,Transactions!$G$6:$G$188,$A10,Transactions!$A$6:$A$188,"P1") -> 580.68 | C10: =SUMIFS(Transactions!$D$6:$D$188,Transactions!$G$6:$G$188,$A10,Transactions!$A$6:$A$188,"P2") -> 501.32 | D10: =SUMIFS(Transactions!$D$6:$D$188,Transactions!$G$6:$G$188,$A10,Transactions!$A$6:$A$188,"P3") -> 196.38 | E10: =SUMIFS(Transactions!$D$6:$D$188,Transactions!$G$6:$G$188,$A10,Transactions!$A$6:$A$188,"P4") -> 267.5 | F10: =SUMIFS(Transactions!$D$6:$D$188,Transactions!$G$6:$G$188,$A10,Transactions!$A$6:$A$188,"P5") -> 175.46 | G10: =SUM(B10:F10) -> 1721.34 | H10: =AVERAGE(B10:E10) -> 386.47 | I10: =IF($G$20=0,0,G10/$G$20) -> 0.13238256 | J10: 390 | K10: =INDEX(B10:F10,MATCH($B$4,$B$6:$F$6,0)) -> 267.5 | L10: =J10-K10 -> 122.5 | M10: =RANK(G10,$G$8:$G$19) -> 3
A11: Stock and supplies | B11: =SUMIFS(Transactions!$D$6:$D$188,Transactions!$G$6:$G$188,$A11,Transactions!$A$6:$A$188,"P1") -> 629.5 | C11: =SUMIFS(Transactions!$D$6:$D$188,Transactions!$G$6:$G$188,$A11,Transactions!$A$6:$A$188,"P2") -> 395.96 | D11: =SUMIFS(Transactions!$D$6:$D$188,Transactions!$G$6:$G$188,$A11,Transactions!$A$6:$A$188,"P3") -> 1136.04 | E11: =SUMIFS(Transactions!$D$6:$D$188,Transactions!$G$6:$G$188,$A11,Transactions!$A$6:$A$188,"P4") -> 124.83 | F11: =SUMIFS(Transactions!$D$6:$D$188,Transactions!$G$6:$G$188,$A11,Transactions!$A$6:$A$188,"P5") -> 479.69 | G11: =SUM(B11:F11) -> 2766.02 | H11: =AVERAGE(B11:E11) -> 571.5825 | I11: =IF($G$20=0,0,G11/$G$20) -> 0.21272544 | J11: 580 | K11: =INDEX(B11:F11,MATCH($B$4,$B$6:$F$6,0)) -> 124.83 | L11: =J11-K11 -> 455.17 | M11: =RANK(G11,$G$8:$G$19) -> 2
A12: Cash withdrawals | B12: =SUMIFS(Transactions!$D$6:$D$188,Transactions!$G$6:$G$188,$A12,Transactions!$A$6:$A$188,"P1") -> 32.29 | C12: =SUMIFS(Transactions!$D$6:$D$188,Transactions!$G$6:$G$188,$A12,Transactions!$A$6:$A$188,"P2") -> 102.37 | D12: =SUMIFS(Transactions!$D$6:$D$188,Transactions!$G$6:$G$188,$A12,Transactions!$A$6:$A$188,"P3") -> 115.6 | E12: =SUMIFS(Transactions!$D$6:$D$188,Transactions!$G$6:$G$188,$A12,Transactions!$A$6:$A$188,"P4") -> 207.34 | F12: =SUMIFS(Transactions!$D$6:$D$188,Transactions!$G$6:$G$188,$A12,Transactions!$A$6:$A$188,"P5") -> 52.39 | G12: =SUM(B12:F12) -> 509.99 | H12: =AVERAGE(B12:E12) -> 114.4 | I12: =IF($G$20=0,0,G12/$G$20) -> 0.039221643 | J12: 120 | K12: =INDEX(B12:F12,MATCH($B$4,$B$6:$F$6,0)) -> 207.34 | L12: =J12-K12 -> -87.34 | M12: =RANK(G12,$G$8:$G$19) -> 5
A13: Bank charges | B13: =SUMIFS(Transactions!$D$6:$D$188,Transactions!$G$6:$G$188,$A13,Transactions!$A$6:$A$188,"P1") -> 8.5 | C13: =SUMIFS(Transactions!$D$6:$D$188,Transactions!$G$6:$G$188,$A13,Transactions!$A$6:$A$188,"P2") -> 8.5 | D13: =SUMIFS(Transactions!$D$6:$D$188,Transactions!$G$6:$G$188,$A13,Transactions!$A$6:$A$188,"P3") -> 8.5 | E13: =SUMIFS(Transactions!$D$6:$D$188,Transactions!$G$6:$G$188,$A13,Transactions!$A$6:$A$188,"P4") -> 8.5 | F13: =SUMIFS(Transactions!$D$6:$D$188,Transactions!$G$6:$G$188,$A13,Transactions!$A$6:$A$188,"P5") -> 8.5 | G13: =SUM(B13:F13) -> 42.5 | H13: =AVERAGE(B13:E13) -> 8.5 | I13: =IF($G$20=0,0,G13/$G$20) -> 0.0032685343 | J13: 10 | K13: =INDEX(B13:F13,MATCH($B$4,$B$6:$F$6,0)) -> 8.5 | L13: =J13-K13 -> 1.5 | M13: =RANK(G13,$G$8:$G$19) -> 11
A14: Subscriptions and utilities | B14: =SUMIFS(Transactions!$D$6:$D$188,Transactions!$G$6:$G$188,$A14,Transactions!$A$6:$A$188,"P1") -> 8.2 | C14: =SUMIFS(Transactions!$D$6:$D$188,Transactions!$G$6:$G$188,$A14,Transactions!$A$6:$A$188,"P2") -> 8.2 | D14: =SUMIFS(Transactions!$D$6:$D$188,Transactions!$G$6:$G$188,$A14,Transactions!$A$6:$A$188,"P3") -> 8.2 | E14: =SUMIFS(Transactions!$D$6:$D$188,Transactions!$G$6:$G$188,$A14,Transactions!$A$6:$A$188,"P4") -> 8.2 | F14: =SUMIFS(Transactions!$D$6:$D$188,Transactions!$G$6:$G$188,$A14,Transactions!$A$6:$A$188,"P5") -> 8.2 | G14: =SUM(B14:F14) -> 41 | H14: =AVERAGE(B14:E14) -> 8.2 | I14: =IF($G$20=0,0,G14/$G$20) -> 0.0031531743 | J14: 10 | K14: =INDEX(B14:F14,MATCH($B$4,$B$6:$F$6,0)) -> 8.2 | L14: =J14-K14 -> 1.8 | M14: =RANK(G14,$G$8:$G$19) -> 12
A15: Parking | B15: =SUMIFS(Transactions!$D$6:$D$188,Transactions!$G$6:$G$188,$A15,Transactions!$A$6:$A$188,"P1") -> 17.49 | C15: =SUMIFS(Transactions!$D$6:$D$188,Transactions!$G$6:$G$188,$A15,Transactions!$A$6:$A$188,"P2") -> 0 | D15: =SUMIFS(Transactions!$D$6:$D$188,Transactions!$G$6:$G$188,$A15,Transactions!$A$6:$A$188,"P3") -> 0 | E15: =SUMIFS(Transactions!$D$6:$D$188,Transactions!$G$6:$G$188,$A15,Transactions!$A$6:$A$188,"P4") -> 20.44 | F15: =SUMIFS(Transactions!$D$6:$D$188,Transactions!$G$6:$G$188,$A15,Transactions!$A$6:$A$188,"P5") -> 14.93 | G15: =SUM(B15:F15) -> 52.86 | H15: =AVERAGE(B15:E15) -> 9.4825 | I15: =IF($G$20=0,0,G15/$G$20) -> 0.0040652876 | J15: 10 | K15: =INDEX(B15:F15,MATCH($B$4,$B$6:$F$6,0)) -> 20.44 | L15: =J15-K15 -> -10.44 | M15: =RANK(G15,$G$8:$G$19) -> 9
A16: Donations | B16: =SUMIFS(Transactions!$D$6:$D$188,Transactions!$G$6:$G$188,$A16,Transactions!$A$6:$A$188,"P1") -> 60.97 | C16: =SUMIFS(Transactions!$D$6:$D$188,Transactions!$G$6:$G$188,$A16,Transactions!$A$6:$A$188,"P2") -> 55.08 | D16: =SUMIFS(Transactions!$D$6:$D$188,Transactions!$G$6:$G$188,$A16,Transactions!$A$6:$A$188,"P3") -> 26.55 | E16: =SUMIFS(Transactions!$D$6:$D$188,Transactions!$G$6:$G$188,$A16,Transactions!$A$6:$A$188,"P4") -> 0 | F16: =SUMIFS(Transactions!$D$6:$D$188,Transactions!$G$6:$G$188,$A16,Transactions!$A$6:$A$188,"P5") -> 27.98 | G16: =SUM(B16:F16) -> 170.58 | H16: =AVERAGE(B16:E16) -> 35.65 | I16: =IF($G$20=0,0,G16/$G$20) -> 0.013118743 | J16: 40 | K16: =INDEX(B16:F16,MATCH($B$4,$B$6:$F$6,0)) -> 0 | L16: =J16-K16 -> 40 | M16: =RANK(G16,$G$8:$G$19) -> 7
A17: Meals and subsistence | B17: =SUMIFS(Transactions!$D$6:$D$188,Transactions!$G$6:$G$188,$A17,Transactions!$A$6:$A$188,"P1") -> 17.39 | C17: =SUMIFS(Transactions!$D$6:$D$188,Transactions!$G$6:$G$188,$A17,Transactions!$A$6:$A$188,"P2") -> 11.52 | D17: =SUMIFS(Transactions!$D$6:$D$188,Transactions!$G$6:$G$188,$A17,Transactions!$A$6:$A$188,"P3") -> 7.25 | E17: =SUMIFS(Transactions!$D$6:$D$188,Transactions!$G$6:$G$188,$A17,Transactions!$A$6:$A$188,"P4") -> 36.59 | F17: =SUMIFS(Transactions!$D$6:$D$188,Transactions!$G$6:$G$188,$A17,Transactions!$A$6:$A$188,"P5") -> 0 | G17: =SUM(B17:F17) -> 72.75 | H17: =AVERAGE(B17:E17) -> 18.1875 | I17: =IF($G$20=0,0,G17/$G$20) -> 0.0055949617 | J17: 20 | K17: =INDEX(B17:F17,MATCH($B$4,$B$6:$F$6,0)) -> 36.59 | L17: =J17-K17 -> -16.59 | M17: =RANK(G17,$G$8:$G$19) -> 8
A18: Health and welfare | B18: =SUMIFS(Transactions!$D$6:$D$188,Transactions!$G$6:$G$188,$A18,Transactions!$A$6:$A$188,"P1") -> 9.27 | C18: =SUMIFS(Transactions!$D$6:$D$188,Transactions!$G$6:$G$188,$A18,Transactions!$A$6:$A$188,"P2") -> 17.45 | D18: =SUMIFS(Transactions!$D$6:$D$188,Transactions!$G$6:$G$188,$A18,Transactions!$A$6:$A$188,"P3") -> 17.95 | E18: =SUMIFS(Transactions!$D$6:$D$188,Transactions!$G$6:$G$188,$A18,Transactions!$A$6:$A$188,"P4") -> 0 | F18: =SUMIFS(Transactions!$D$6:$D$188,Transactions!$G$6:$G$188,$A18,Transactions!$A$6:$A$188,"P5") -> 0 | G18: =SUM(B18:F18) -> 44.67 | H18: =AVERAGE(B18:E18) -> 11.1675 | I18: =IF($G$20=0,0,G18/$G$20) -> 0.0034354218 | J18: 20 | K18: =INDEX(B18:F18,MATCH($B$4,$B$6:$F$6,0)) -> 0 | L18: =J18-K18 -> 20 | M18: =RANK(G18,$G$8:$G$19) -> 10
A19: Office and equipment | B19: =SUMIFS(Transactions!$D$6:$D$188,Transactions!$G$6:$G$188,$A19,Transactions!$A$6:$A$188,"P1") -> 99.39 | C19: =SUMIFS(Transactions!$D$6:$D$188,Transactions!$G$6:$G$188,$A19,Transactions!$A$6:$A$188,"P2") -> 66.04 | D19: =SUMIFS(Transactions!$D$6:$D$188,Transactions!$G$6:$G$188,$A19,Transactions!$A$6:$A$188,"P3") -> 0 | E19: =SUMIFS(Transactions!$D$6:$D$188,Transactions!$G$6:$G$188,$A19,Transactions!$A$6:$A$188,"P4") -> 20.36 | F19: =SUMIFS(Transactions!$D$6:$D$188,Transactions!$G$6:$G$188,$A19,Transactions!$A$6:$A$188,"P5") -> 70.27 | G19: =SUM(B19:F19) -> 256.06 | H19: =AVERAGE(B19:E19) -> 46.4475 | I19: =IF($G$20=0,0,G19/$G$20) -> 0.019692727 | J19: 50 | K19: =INDEX(B19:F19,MATCH($B$4,$B$6:$F$6,0)) -> 20.36 | L19: =J19-K19 -> 29.64 | M19: =RANK(G19,$G$8:$G$19) -> 6
A20: Total spending | B20: =SUM(B8:B19) -> 2038.68 | C20: =SUM(C8:C19) -> 2741.44 | D20: =SUM(D8:D19) -> 3841.47 | E20: =SUM(E8:E19) -> 3443.76 | F20: =SUM(F8:F19) -> 937.42 | G20: =SUM(G8:G19) -> 13002.77 | H20: =SUM(H8:H19) -> 3016.3375 | J20: =SUM(J8:J19) -> 3060 | K20: =SUM(K8:K19) -> 3443.76 | L20: =SUM(L8:L19) -> -383.76
A22: Income
A23: Income: client receipts | B23: =SUMIFS(Transactions!$E$6:$E$188,Transactions!$G$6:$G$188,$A23,Transactions!$A$6:$A$188,"P1") -> 1501.21 | C23: =SUMIFS(Transactions!$E$6:$E$188,Transactions!$G$6:$G$188,$A23,Transactions!$A$6:$A$188,"P2") -> 673.45 | D23: =SUMIFS(Transactions!$E$6:$E$188,Transactions!$G$6:$G$188,$A23,Transactions!$A$6:$A$188,"P3") -> 4305 | E23: =SUMIFS(Transactions!$E$6:$E$188,Transactions!$G$6:$G$188,$A23,Transactions!$A$6:$A$188,"P4") -> 2582.71 | F23: =SUMIFS(Transactions!$E$6:$E$188,Transactions!$G$6:$G$188,$A23,Transactions!$A$6:$A$188,"P5") -> 245.88 | G23: =SUM(B23:F23) -> 9308.25 | H23: =AVERAGE(B23:E23) -> 2265.5925 | K23: =INDEX(B23:F23,MATCH($B$4,$B$6:$F$6,0)) -> 2582.71
A24: Income: transfers in | B24: =SUMIFS(Transactions!$E$6:$E$188,Transactions!$G$6:$G$188,$A24,Transactions!$A$6:$A$188,"P1") -> 1125 | C24: =SUMIFS(Transactions!$E$6:$E$188,Transactions!$G$6:$G$188,$A24,Transactions!$A$6:$A$188,"P2") -> 850 | D24: =SUMIFS(Transactions!$E$6:$E$188,Transactions!$G$6:$G$188,$A24,Transactions!$A$6:$A$188,"P3") -> 450 | E24: =SUMIFS(Transactions!$E$6:$E$188,Transactions!$G$6:$G$188,$A24,Transactions!$A$6:$A$188,"P4") -> 175 | F24: =SUMIFS(Transactions!$E$6:$E$188,Transactions!$G$6:$G$188,$A24,Transactions!$A$6:$A$188,"P5") -> 200 | G24: =SUM(B24:F24) -> 2800 | H24: =AVERAGE(B24:E24) -> 650 | K24: =INDEX(B24:F24,MATCH($B$4,$B$6:$F$6,0)) -> 175
A25: Total income | B25: =SUM(B23:B24) -> 2626.21 | C25: =SUM(C23:C24) -> 1523.45 | D25: =SUM(D23:D24) -> 4755 | E25: =SUM(E23:E24) -> 2757.71 | F25: =SUM(F23:F24) -> 445.88 | G25: =SUM(G23:G24) -> 12108.25 | H25: =SUM(H23:H24) -> 2915.5925 | K25: =SUM(K23:K24) -> 2757.71
A27: Net cash flow | B27: =B25-B20 -> 587.53 | C27: =C25-C20 -> -1217.99 | D27: =D25-D20 -> 913.53 | E27: =E25-E20 -> -686.05 | F27: =F25-F20 -> -491.54 | G27: =G25-G20 -> -894.52 | H27: =H25-H20 -> -100.745 | K27: =K25-K20 -> -686.05
A29: P5 is a part month (23 Sep to 11 Oct, the final statement), so the monthly average uses P1 to P4.
A30: Proposed monthly budget: the P1 to P4 average rounded up to the nearest £10, as a starting point to edit.

Sheet Transactions
A1: Transactions
A2: Running balance, period and category are calculated. Synthetic data.
A3: Opening balance (from statement 1) | D3: 2410
A5: Period | B5: Date | C5: Description | D5: Money out (£) | E5: Money in (£) | F5: Balance (£) | G5: Category | H5: Month
A6: =INDEX(Reconciliation!$A$6:$A$10,MATCH(B6,Reconciliation!$B$6:$B$10,1)) -> P1 | B6: 44702 | C6: Card payment to Wholesale Club 910 on 21 May | D6: 95.06 | F6: =$D$3-N(D6)+N(E6) -> 2314.94 | G6: =IFERROR(LOOKUP(2^15,SEARCH('Category Rules'!$A$5:$A$23,C6),'Category Rules'!$B$5:$B$23),"Uncategorised") -> Stock and supplies | H6: =TEXT(B6,"mmm yyyy") -> May 2022
A7: =INDEX(Reconciliation!$A$6:$A$10,MATCH(B7,Reconciliation!$B$6:$B$10,1)) -> P1 | B7: 44702 | C7: Direct credit from Client B Ltd | E7: 353.78 | F7: =F6-N(D7)+N(E7) -> 2668.72 | G7: =IFERROR(LOOKUP(2^15,SEARCH('Category Rules'!$A$5:$A$23,C7),'Category Rules'!$B$5:$B$23),"Uncategorised") -> Income: client receipts | H7: =TEXT(B7,"mmm yyyy") -> May 2022
A8: =INDEX(Reconciliation!$A$6:$A$10,MATCH(B8,Reconciliation!$B$6:$B$10,1)) -> P1 | B8: 44703 | C8: Card payment to Charity Shop 545 on 22 May | D8: 14.88 | F8: =F7-N(D8)+N(E8) -> 2653.84 | G8: =IFERROR(LOOKUP(2^15,SEARCH('Category Rules'!$A$5:$A$23,C8),'Category Rules'!$B$5:$B$23),"Uncategorised") -> Donations | H8: =TEXT(B8,"mmm yyyy") -> May 2022
A9: =INDEX(Reconciliation!$A$6:$A$10,MATCH(B9,Reconciliation!$B$6:$B$10,1)) -> P1 | B9: 44704 | C9: Direct credit from Client B Ltd | E9: 74.91 | F9: =F8-N(D9)+N(E9) -> 2728.75 | G9: =IFERROR(LOOKUP(2^15,SEARCH('Category Rules'!$A$5:$A$23,C9),'Category Rules'!$B$5:$B$23),"Uncategorised") -> Income: client receipts | H9: =TEXT(B9,"mmm yyyy") -> May 2022
A10: =INDEX(Reconciliation!$A$6:$A$10,MATCH(B10,Reconciliation!$B$6:$B$10,1)) -> P1 | B10: 44704 | C10: Internet banking transfer to savings account | D10: 300 | F10: =F9-N(D10)+N(E10) -> 2428.75 | G10: =IFERROR(LOOKUP(2^15,SEARCH('Category Rules'!$A$5:$A$23,C10),'Category Rules'!$B$5:$B$23),"Uncategorised") -> Transfers out | H10: =TEXT(B10,"mmm yyyy") -> May 2022
A11: =INDEX(Reconciliation!$A$6:$A$10,MATCH(B11,Reconciliation!$B$6:$B$10,1)) -> P1 | B11: 44705 | C11: Card payment to Hardware Store on 22 May | D11: 23.31 | F11: =F10-N(D11)+N(E11) -> 2405.44 | G11: =IFERROR(LOOKUP(2^15,SEARCH('Category Rules'!$A$5:$A$23,C11),'Category Rules'!$B$5:$B$23),"Uncategorised") -> Office and equipment | H11: =TEXT(B11,"mmm yyyy") -> May 2022
A12: =INDEX(Reconciliation!$A$6:$A$10,MATCH(B12,Reconciliation!$B$6:$B$10,1)) -> P1 | B12: 44706 | C12: Card payment to High Street Cafe on 23 May | D12: 1.41 | F12: =F11-N(D12)+N(E12) -> 2404.03 | G12: =IFERROR(LOOKUP(2^15,SEARCH('Category Rules'!$A$5:$A$23,C12),'Category Rules'!$B$5:$B$23),"Uncategorised") -> Meals and subsistence | H12: =TEXT(B12,"mmm yyyy") -> May 2022
A13: =INDEX(Reconciliation!$A$6:$A$10,MATCH(B13,Reconciliation!$B$6:$B$10,1)) -> P1 | B13: 44707 | C13: Internet banking transfer from savings account | E13: 50 | F13: =F12-N(D13)+N(E13) -> 2454.03 | G13: =IFERROR(LOOKUP(2^15,SEARCH('Category Rules'!$A$5:$A$23,C13),'Category Rules'!$B$5:$B$23),"Uncategorised") -> Income: transfers in | H13: =TEXT(B13,"mmm yyyy") -> May 2022
A14: =INDEX(Reconciliation!$A$6:$A$10,MATCH(B14,Reconciliation!$B$6:$B$10,1)) -> P1 | B14: 44707 | C14: Card payment to Fuel Station 997 on 24 May | D14: 66.79 | F14: =F13-N(D14)+N(E14) -> 2387.24 | G14: =IFERROR(LOOKUP(2^15,SEARCH('Category Rules'!$A$5:$A$23,C14),'Category Rules'!$B$5:$B$23),"Uncategorised") -> Fuel and vehicle | H14: =TEXT(B14,"mmm yyyy") -> May 2022
A15: =INDEX(Reconciliation!$A$6:$A$10,MATCH(B15,Reconciliation!$B$6:$B$10,1)) -> P1 | B15: 44707 | C15: Internet banking transfer from savings account | E15: 50 | F15: =F14-N(D15)+N(E15) -> 2437.24 | G15: =IFERROR(LOOKUP(2^15,SEARCH('Category Rules'!$A$5:$A$23,C15),'Category Rules'!$B$5:$B$23),"Uncategorised") -> Income: transfers in | H15: =TEXT(B15,"mmm yyyy") -> May 2022
A16: =INDEX(Reconciliation!$A$6:$A$10,MATCH(B16,Reconciliation!$B$6:$B$10,1)) -> P1 | B16: 44708 | C16: Direct credit from Client B Ltd | E16: 406.62 | F16: =F15-N(D16)+N(E16) -> 2843.86 | G16: =IFERROR(LOOKUP(2^15,SEARCH('Category Rules'!$A$5:$A$23,C16),'Category Rules'!$B$5:$B$23),"Uncategorised") -> Income: client receipts | H16: =TEXT(B16,"mmm yyyy") -> May 2022
A17: =INDEX(Reconciliation!$A$6:$A$10,MATCH(B17,Reconciliation!$B$6:$B$10,1)) -> P1 | B17: 44710 | C17: Card payment to Stationers Ltd on 29 May | D17: 45.5 | F17: =F16-N(D17)+N(E17) -> 2798.36 | G17: =IFERROR(LOOKUP(2^15,SEARCH('Category Rules'!$A$5:$A$23,C17),'Category Rules'!$B$5:$B$23),"Uncategorised") -> Office and equipment | H17: =TEXT(B17,"mmm yyyy") -> May 2022
A18: =INDEX(Reconciliation!$A$6:$A$10,MATCH(B18,Reconciliation!$B$6:$B$10,1)) -> P1 | B18: 44710 | C18: Card payment to Pharmacy 827 on 29 May | D18: 9.27 | F18: =F17-N(D18)+N(E18) -> 2789.09 | G18: =IFERROR(LOOKUP(2^15,SEARCH('Category Rules'!$A$5:$A$23,C18),'Category Rules'!$B$5:$B$23),"Uncategorised") -> Health and welfare | H18: =TEXT(B18,"mmm yyyy") -> May 2022
A19: =INDEX(Reconciliation!$A$6:$A$10,MATCH(B19,Reconciliation!$B$6:$B$10,1)) -> P1 | B19: 44711 | C19: Direct debit to Telecom Co | D19: 8.2 | F19: =F18-N(D19)+N(E19) -> 2780.89 | G19: =IFERROR(LOOKUP(2^15,SEARCH('Category Rules'!$A$5:$A$23,C19),'Category Rules'!$B$5:$B$23),"Uncategorised") -> Subscriptions and utilities | H19: =TEXT(B19,"mmm yyyy") -> May 2022
A20: =INDEX(Reconciliation!$A$6:$A$10,MATCH(B20,Reconciliation!$B$6:$B$10,1)) -> P1 | B20: 44711 | C20: Card payment to Charity Shop 595 on 29 May | D20: 22.36 | F20: =F19-N(D20)+N(E20) -> 2758.53 | G20: =IFERROR(LOOKUP(2^15,SEARCH('Category Rules'!$A$5:$A$23,C20),'Category Rules'!$B$5:$B$23),"Uncategorised") -> Donations | H20: =TEXT(B20,"mmm yyyy") -> May 2022
A21: =INDEX(Reconciliation!$A$6:$A$10,MATCH(B21,Reconciliation!$B$6:$B$10,1)) -> P1 | B21: 44713 | C21: Card payment to Charity Shop 141 on 30 May | D21: 2.35 | F21: =F20-N(D21)+N(E21) -> 2756.18 | G21: =IFERROR(LOOKUP(2^15,SEARCH('Category Rules'!$A$5:$A$23,C21),'Category Rules'!$B$5:$B$23),"Uncategorised") -> Donations | H21: =TEXT(B21,"mmm yyyy") -> Jun 2022
A22: =INDEX(Reconciliation!$A$6:$A$10,MATCH(B22,Reconciliation!$B$6:$B$10,1)) -> P1 | B22: 44714 | C22: Card payment to Wholesale Club 683 on 01 Jun | D22: 77.63 | F22: =F21-N(D22)+N(E22) -> 2678.55 | G22: =IFERROR(LOOKUP(2^15,SEARCH('Category Rules'!$A$5:$A$23,C22),'Category Rules'!$B$5:$B$23),"Uncategorised") -> Stock and supplies | H22: =TEXT(B22,"mmm yyyy") -> Jun 2022
A23: =INDEX(Reconciliation!$A$6:$A$10,MATCH(B23,Reconciliation!$B$6:$B$10,1)) -> P1 | B23: 44714 | C23: Card payment to Cash and Carry 923 on 01 Jun | D23: 22.96 | F23: =F22-N(D23)+N(E23) -> 2655.59 | G23: =IFERROR(LOOKUP(2^15,SEARCH('Category Rules'!$A$5:$A$23,C23),'Category Rules'!$B$5:$B$23),"Uncategorised") -> Stock and supplies | H23: =TEXT(B23,"mmm yyyy") -> Jun 2022
A24: =INDEX(Reconciliation!$A$6:$A$10,MATCH(B24,Reconciliation!$B$6:$B$10,1)) -> P1 | B24: 44715 | C24: Direct credit from Client B Ltd | E24: 329.44 | F24: =F23-N(D24)+N(E24) -> 2985.03 | G24: =IFERROR(LOOKUP(2^15,SEARCH('Category Rules'!$A$5:$A$23,C24),'Category Rules'!$B$5:$B$23),"Uncategorised") -> Income: client receipts | H24: =TEXT(B24,"mmm yyyy") -> Jun 2022
A25: =INDEX(Reconciliation!$A$6:$A$10,MATCH(B25,Reconciliation!$B$6:$B$10,1)) -> P1 | B25: 44716 | C25: Internet banking transfer to savings account | D25: 25 | F25: =F24-N(D25)+N(E25) -> 2960.03 | G25: =IFERROR(LOOKUP(2^15,SEARCH('Category Rules'!$A$5:$A$23,C25),'Category Rules'!$B$5:$B$23),"Uncategorised") -> Transfers out | H25: =TEXT(B25,"mmm yyyy") -> Jun 2022
A26: =INDEX(Reconciliation!$A$6:$A$10,MATCH(B26,Reconciliation!$B$6:$B$10,1)) -> P1 | B26: 44716 | C26: Internet banking transfer from savings account | E26: 25 | F26: =F25-N(D26)+N(E26) -> 2985.03 | G26: =IFERROR(LOOKUP(2^15,SEARCH('Category Rules'!$A$5:$A$23,C26),'Category Rules'!$B$5:$B$23),"Uncategorised") -> Income: transfers in | H26: =TEXT(B26,"mmm yyyy") -> Jun 2022
A27: =INDEX(Reconciliation!$A$6:$A$10,MATCH(B27,Reconciliation!$B$6:$B$10,1)) -> P1 | B27: 44716 | C27: Card payment to Garage Services on 04 Jun | D27: 66.78 | F27: =F26-N(D27)+N(E27) -> 2918.25 | G27: =IFERROR(LOOKUP(2^15,SEARCH('Category Rules'!$A$5:$A$23,C27),'Category Rules'!$B$5:$B$23),"Uncategorised") -> Fuel and vehicle | H27: =TEXT(B27,"mmm yyyy") -> Jun 2022
A28: =INDEX(Reconciliation!$A$6:$A$10,MATCH(B28,Reconciliation!$B$6:$B$10,1)) -> P1 | B28: 44716 | C28: Card payment to Fuel Station 827 on 03 Jun | D28: 55.67 | F28: =F27-N(D28)+N(E28) -> 2862.58 | G28: =IFERROR(LOOKUP(2^15,SEARCH('Category Rules'!$A$5:$A$23,C28),'Category Rules'!$B$5:$B$23),"Uncategorised") -> Fuel and vehicle | H28: =TEXT(B28,"mmm yyyy") -> Jun 2022
A29: =INDEX(Reconciliation!$A$6:$A$10,MATCH(B29,Reconciliation!$B$6:$B$10,1)) -> P1 | B29: 44716 | C29: Card payment to Fuel Station 854 on 03 Jun | D29: 87.27 | F29: =F28-N(D29)+N(E29) -> 2775.31 | G29: =IFERROR(LOOKUP(2^15,SEARCH('Category Rules'!$A$5:$A$23,C29),'Category Rules'!$B$5:$B$23),"Uncategorised") -> Fuel and vehicle | H29: =TEXT(B29,"mmm yyyy") -> Jun 2022
A30: =INDEX(Reconciliation!$A$6:$A$10,MATCH(B30,Reconciliation!$B$6:$B$10,1)) -> P1 | B30: 44716 | C30: Card payment to City Car Park on 03 Jun | D30: 4.08 | F30: =F29-N(D30)+N(E30) -> 2771.23 | G30: =IFERROR(LOOKUP(2^15,SEARCH('Category Rules'!$A$5:$A$23,C30),'Category Rules'!$B$5:$B$23),"Uncategorised") -> Parking | H30: =TEXT(B30,"mmm yyyy") -> Jun 2022
A31: =INDEX(Reconciliation!$A$6:$A$10,MATCH(B31,Reconciliation!$B$6:$B$10,1)) -> P1 | B31: 44717 | C31: Commission charges for the period | D31: 8.5 | F31: =F30-N(D31)+N(E31) -> 2762.73 | G31: =IFERROR(LOOKUP(2^15,SEARCH('Category Rules'!$A$5:$A$23,C31),'Category Rules'!$B$5:$B$23),"Uncategorised") -> Bank charges | H31: =TEXT(B31,"mmm yyyy") -> Jun 2022
A32: =INDEX(Reconciliation!$A$6:$A$10,MATCH(B32,Reconciliation!$B$6:$B$10,1)) -> P1 | B32: 44718 | C32: Card payment to Charity Shop 632 on 05 Jun | D32: 2.98 | F32: =F31-N(D32)+N(E32) -> 2759.75 | G32: =IFERROR(LOOKUP(2^15,SEARCH('Category Rules'!$A$5:$A$23,C32),'Category Rules'!$B$5:$B$23),"Uncategorised") -> Donations | H32: =TEXT(B32,"mmm yyyy") -> Jun 2022
A33: =INDEX(Reconciliation!$A$6:$A$10,MATCH(B33,Reconciliation!$B$6:$B$10,1)) -> P1 | B33: 44718 | C33: Card payment to Garage Services on 04 Jun | D33: 56.55 | F33: =F32-N(D33)+N(E33) -> 2703.2 | G33: =IFERROR(LOOKUP(2^15,SEARCH('Category Rules'!$A$5:$A$23,C33),'Category Rules'!$B$5:$B$23),"Uncategorised") -> Fuel and vehicle | H33: =TEXT(B33,"mmm yyyy") -> Jun 2022
A34: =INDEX(Reconciliation!$A$6:$A$10,MATCH(B34,Reconciliation!$B$6:$B$10,1)) -> P1 | B34: 44719 | C34: Card payment to High Street Cafe on 05 Jun | D34: 8.69 | F34: =F33-N(D34)+N(E34) -> 2694.51 | G34: =IFERROR(LOOKUP(2^15,SEARCH('Category Rules'!$A$5:$A$23,C34),'Category Rules'!$B$5:$B$23),"Uncategorised") -> Meals and subsistence | H34: =TEXT(B34,"mmm yyyy") -> Jun 2022
A35: =INDEX(Reconciliation!$A$6:$A$10,MATCH(B35,Reconciliation!$B$6:$B$10,1)) -> P1 | B35: 44720 | C35: Card payment to High Street Cafe on 08 Jun | D35: 7.29 | F35: =F34-N(D35)+N(E35) -> 2687.22 | G35: =IFERROR(LOOKUP(2^15,SEARCH('Category Rules'!$A$5:$A$23,C35),'Category Rules'!$B$5:$B$23),"Uncategorised") -> Meals and subsistence | H35: =TEXT(B35,"mmm yyyy") -> Jun 2022
A36: =INDEX(Reconciliation!$A$6:$A$10,MATCH(B36,Reconciliation!$B$6:$B$10,1)) -> P1 | B36: 44723 | C36: Card payment to Charity Shop 366 on 11 Jun | D36: 18.4 | F36: =F35-N(D36)+N(E36) -> 2668.82 | G36: =IFERROR(LOOKUP(2^15,SEARCH('Category Rules'!$A$5:$A$23,C36),'Category Rules'!$B$5:$B$23),"Uncategorised") -> Donations | H36: =TEXT(B36,"mmm yyyy") -> Jun 2022
A37: =INDEX(Reconciliation!$A$6:$A$10,MATCH(B37,Reconciliation!$B$6:$B$10,1)) -> P1 | B37: 44723 | C37: Card payment to City Car Park on 11 Jun | D37: 13.41 | F37: =F36-N(D37)+N(E37) -> 2655.41 | G37: =IFERROR(LOOKUP(2^15,SEARCH('Category Rules'!$A$5:$A$23,C37),'Category Rules'!$B$5:$B$23),"Uncategorised") -> Parking | H37: =TEXT(B37,"mmm yyyy") -> Jun 2022
A38: =INDEX(Reconciliation!$A$6:$A$10,MATCH(B38,Reconciliation!$B$6:$B$10,1)) -> P1 | B38: 44724 | C38: Direct credit from Client B Ltd | E38: 336.46 | F38: =F37-N(D38)+N(E38) -> 2991.87 | G38: =IFERROR(LOOKUP(2^15,SEARCH('Category Rules'!$A$5:$A$23,C38),'Category Rules'!$B$5:$B$23),"Uncategorised") -> Income: client receipts | H38: =TEXT(B38,"mmm yyyy") -> Jun 2022
A39: =INDEX(Reconciliation!$A$6:$A$10,MATCH(B39,Reconciliation!$B$6:$B$10,1)) -> P1 | B39: 44725 | C39: Card payment to Fuel Station 631 on 13 Jun | D39: 44.36 | F39: =F38-N(D39)+N(E39) -> 2947.51 | G39: =IFERROR(LOOKUP(2^15,SEARCH('Category Rules'!$A$5:$A$23,C39),'Category Rules'!$B$5:$B$23),"Uncategorised") -> Fuel and vehicle | H39: =TEXT(B39,"mmm yyyy") -> Jun 2022
A40: =INDEX(Reconciliation!$A$6:$A$10,MATCH(B40,Reconciliation!$B$6:$B$10,1)) -> P1 | B40: 44725 | C40: Internet banking transfer from savings account | E40: 1000 | F40: =F39-N(D40)+N(E40) -> 3947.51 | G40: =IFERROR(LOOKUP(2^15,SEARCH('Category Rules'!$A$5:$A$23,C40),'Category Rules'!$B$5:$B$23),"Uncategorised") -> Income: transfers in | H40: =TEXT(B40,"mmm yyyy") -> Jun 2022
A41: =INDEX(Reconciliation!$A$6:$A$10,MATCH(B41,Reconciliation!$B$6:$B$10,1)) -> P1 | B41: 44726 | C41: Card payment to Fuel Station 743 on 14 Jun | D41: 83.68 | F41: =F40-N(D41)+N(E41) -> 3863.83 | G41: =IFERROR(LOOKUP(2^15,SEARCH('Category Rules'!$A$5:$A$23,C41),'Category Rules'!$B$5:$B$23),"Uncategorised") -> Fuel and vehicle | H41: =TEXT(B41,"mmm yyyy") -> Jun 2022
A42: =INDEX(Reconciliation!$A$6:$A$10,MATCH(B42,Reconciliation!$B$6:$B$10,1)) -> P1 | B42: 44727 | C42: Card payment to Corner Grocer on 13 Jun | D42: 35.07 | F42: =F41-N(D42)+N(E42) -> 3828.76 | G42: =IFERROR(LOOKUP(2^15,SEARCH('Category Rules'!$A$5:$A$23,C42),'Category Rules'!$B$5:$B$23),"Uncategorised") -> Stock and supplies | H42: =TEXT(B42,"mmm yyyy") -> Jun 2022
A43: =INDEX(Reconciliation!$A$6:$A$10,MATCH(B43,Reconciliation!$B$6:$B$10,1)) -> P1 | B43: 44727 | C43: Card payment to Wholesale Club 831 on 14 Jun | D43: 190.94 | F43: =F42-N(D43)+N(E43) -> 3637.82 | G43: =IFERROR(LOOKUP(2^15,SEARCH('Category Rules'!$A$5:$A$23,C43),'Category Rules'!$B$5:$B$23),"Uncategorised") -> Stock and supplies | H43: =TEXT(B43,"mmm yyyy") -> Jun 2022
A44: =INDEX(Reconciliation!$A$6:$A$10,MATCH(B44,Reconciliation!$B$6:$B$10,1)) -> P1 | B44: 44728 | C44: Card payment to Fuel Station 744 on 16 Jun | D44: 73.07 | F44: =F43-N(D44)+N(E44) -> 3564.75 | G44: =IFERROR(LOOKUP(2^15,SEARCH('Category Rules'!$A$5:$A$23,C44),'Category Rules'!$B$5:$B$23),"Uncategorised") -> Fuel and vehicle | H44: =TEXT(B44,"mmm yyyy") -> Jun 2022
A45: =INDEX(Reconciliation!$A$6:$A$10,MATCH(B45,Reconciliation!$B$6:$B$10,1)) -> P1 | B45: 44728 | C45: Card payment to Fuel Station 316 on 15 Jun | D45: 46.51 | F45: =F44-N(D45)+N(E45) -> 3518.24 | G45: =IFERROR(LOOKUP(2^15,SEARCH('Category Rules'!$A$5:$A$23,C45),'Category Rules'!$B$5:$B$23),"Uncategorised") -> Fuel and vehicle | H45: =TEXT(B45,"mmm yyyy") -> Jun 2022
A46: =INDEX(Reconciliation!$A$6:$A$10,MATCH(B46,Reconciliation!$B$6:$B$10,1)) -> P1 | B46: 44732 | C46: Card payment to Wholesale Club 926 on 19 Jun | D46: 207.84 | F46: =F45-N(D46)+N(E46) -> 3310.4 | G46: =IFERROR(LOOKUP(2^15,SEARCH('Category Rules'!$A$5:$A$23,C46),'Category Rules'!$B$5:$B$23),"Uncategorised") -> Stock and supplies | H46: =TEXT(B46,"mmm yyyy") -> Jun 2022
A47: =INDEX(Reconciliation!$A$6:$A$10,MATCH(B47,Reconciliation!$B$6:$B$10,1)) -> P1 | B47: 44733 | C47: Cash machine withdrawal on 19 Jun | D47: 32.29 | F47: =F46-N(D47)+N(E47) -> 3278.11 | G47: =IFERROR(LOOKUP(2^15,SEARCH('Category Rules'!$A$5:$A$23,C47),'Category Rules'!$B$5:$B$23),"Uncategorised") -> Cash withdrawals | H47: =TEXT(B47,"mmm yyyy") -> Jun 2022
A48: =INDEX(Reconciliation!$A$6:$A$10,MATCH(B48,Reconciliation!$B$6:$B$10,1)) -> P1 | B48: 44733 | C48: Card payment to Hardware Store on 20 Jun | D48: 30.58 | F48: =F47-N(D48)+N(E48) -> 3247.53 | G48: =IFERROR(LOOKUP(2^15,SEARCH('Category Rules'!$A$5:$A$23,C48),'Category Rules'!$B$5:$B$23),"Uncategorised") -> Office and equipment | H48: =TEXT(B48,"mmm yyyy") -> Jun 2022
A49: =INDEX(Reconciliation!$A$6:$A$10,MATCH(B49,Reconciliation!$B$6:$B$10,1)) -> P1 | B49: 44734 | C49: Internet banking transfer to savings account | D49: 250 | F49: =F48-N(D49)+N(E49) -> 2997.53 | G49: =IFERROR(LOOKUP(2^15,SEARCH('Category Rules'!$A$5:$A$23,C49),'Category Rules'!$B$5:$B$23),"Uncategorised") -> Transfers out | H49: =TEXT(B49,"mmm yyyy") -> Jun 2022
A50: =INDEX(Reconciliation!$A$6:$A$10,MATCH(B50,Reconciliation!$B$6:$B$10,1)) -> P2 | B50: 44735 | C50: Card payment to Fuel Station 925 on 22 Jun | D50: 86.47 | F50: =F49-N(D50)+N(E50) -> 2911.06 | G50: =IFERROR(LOOKUP(2^15,SEARCH('Category Rules'!$A$5:$A$23,C50),'Category Rules'!$B$5:$B$23),"Uncategorised") -> Fuel and vehicle | H50: =TEXT(B50,"mmm yyyy") -> Jun 2022
A51: =INDEX(Reconciliation!$A$6:$A$10,MATCH(B51,Reconciliation!$B$6:$B$10,1)) -> P2 | B51: 44736 | C51: Internet banking transfer from savings account | E51: 500 | F51: =F50-N(D51)+N(E51) -> 3411.06 | G51: =IFERROR(LOOKUP(2^15,SEARCH('Category Rules'!$A$5:$A$23,C51),'Category Rules'!$B$5:$B$23),"Uncategorised") -> Income: transfers in | H51: =TEXT(B51,"mmm yyyy") -> Jun 2022
A52: =INDEX(Reconciliation!$A$6:$A$10,MATCH(B52,Reconciliation!$B$6:$B$10,1)) -> P2 | B52: 44737 | C52: Internet banking transfer to savings account | D52: 250 | F52: =F51-N(D52)+N(E52) -> 3161.06 | G52: =IFERROR(LOOKUP(2^15,SEARCH('Category Rules'!$A$5:$A$23,C52),'Category Rules'!$B$5:$B$23),"Uncategorised") -> Transfers out | H52: =TEXT(B52,"mmm yyyy") -> Jun 2022
A53: =INDEX(Reconciliation!$A$6:$A$10,MATCH(B53,Reconciliation!$B$6:$B$10,1)) -> P2 | B53: 44737 | C53: Card payment to Wholesale Club 767 on 23 Jun | D53: 94.23 | F53: =F52-N(D53)+N(E53) -> 3066.83 | G53: =IFERROR(LOOKUP(2^15,SEARCH('Category Rules'!$A$5:$A$23,C53),'Category Rules'!$B$5:$B$23),"Uncategorised") -> Stock and supplies | H53: =TEXT(B53,"mmm yyyy") -> Jun 2022
A54: =INDEX(Reconciliation!$A$6:$A$10,MATCH(B54,Reconciliation!$B$6:$B$10,1)) -> P2 | B54: 44737 | C54: Internet banking transfer to savings account | D54: 50 | F54: =F53-N(D54)+N(E54) -> 3016.83 | G54: =IFERROR(LOOKUP(2^15,SEARCH('Category Rules'!$A$5:$A$23,C54),'Category Rules'!$B$5:$B$23),"Uncategorised") -> Transfers out | H54: =TEXT(B54,"mmm yyyy") -> Jun 2022
A55: =INDEX(Reconciliation!$A$6:$A$10,MATCH(B55,Reconciliation!$B$6:$B$10,1)) -> P2 | B55: 44740 | C55: Card payment to Charity Shop 631 on 27 Jun | D55: 14.5 | F55: =F54-N(D55)+N(E55) -> 3002.33 | G55: =IFERROR(LOOKUP(2^15,SEARCH('Category Rules'!$A$5:$A$23,C55),'Category Rules'!$B$5:$B$23),"Uncategorised") -> Donations | H55: =TEXT(B55,"mmm yyyy") -> Jun 2022
A56: =INDEX(Reconciliation!$A$6:$A$10,MATCH(B56,Reconciliation!$B$6:$B$10,1)) -> P2 | B56: 44741 | C56: Direct credit from Client B Ltd | E56: 49.24 | F56: =F55-N(D56)+N(E56) -> 3051.57 | G56: =IFERROR(LOOKUP(2^15,SEARCH('Category Rules'!$A$5:$A$23,C56),'Category Rules'!$B$5:$B$23),"Uncategorised") -> Income: client receipts | H56: =TEXT(B56,"mmm yyyy") -> Jun 2022
A57: =INDEX(Reconciliation!$A$6:$A$10,MATCH(B57,Reconciliation!$B$6:$B$10,1)) -> P2 | B57: 44742 | C57: Direct credit from Client B Ltd | E57: 34.32 | F57: =F56-N(D57)+N(E57) -> 3085.89 | G57: =IFERROR(LOOKUP(2^15,SEARCH('Category Rules'!$A$5:$A$23,C57),'Category Rules'!$B$5:$B$23),"Uncategorised") -> Income: client receipts | H57: =TEXT(B57,"mmm yyyy") -> Jun 2022
A58: =INDEX(Reconciliation!$A$6:$A$10,MATCH(B58,Reconciliation!$B$6:$B$10,1)) -> P2 | B58: 44742 | C58: Card payment to Fuel Station 356 on 30 Jun | D58: 84.74 | F58: =F57-N(D58)+N(E58) -> 3001.15 | G58: =IFERROR(LOOKUP(2^15,SEARCH('Category Rules'!$A$5:$A$23,C58),'Category Rules'!$B$5:$B$23),"Uncategorised") -> Fuel and vehicle | H58: =TEXT(B58,"mmm yyyy") -> Jun 2022
A59: =INDEX(Reconciliation!$A$6:$A$10,MATCH(B59,Reconciliation!$B$6:$B$10,1)) -> P2 | B59: 44743 | C59: Card payment to Pharmacy 629 on 01 Jul | D59: 17.45 | F59: =F58-N(D59)+N(E59) -> 2983.7 | G59: =IFERROR(LOOKUP(2^15,SEARCH('Category Rules'!$A$5:$A$23,C59),'Category Rules'!$B$5:$B$23),"Uncategorised") -> Health and welfare | H59: =TEXT(B59,"mmm yyyy") -> Jul 2022
A60: =INDEX(Reconciliation!$A$6:$A$10,MATCH(B60,Reconciliation!$B$6:$B$10,1)) -> P2 | B60: 44744 | C60: Direct debit to Telecom Co | D60: 8.2 | F60: =F59-N(D60)+N(E60) -> 2975.5 | G60: =IFERROR(LOOKUP(2^15,SEARCH('Category Rules'!$A$5:$A$23,C60),'Category Rules'!$B$5:$B$23),"Uncategorised") -> Subscriptions and utilities | H60: =TEXT(B60,"mmm yyyy") -> Jul 2022
A61: =INDEX(Reconciliation!$A$6:$A$10,MATCH(B61,Reconciliation!$B$6:$B$10,1)) -> P2 | B61: 44744 | C61: Direct credit from Client B Ltd | E61: 287.68 | F61: =F60-N(D61)+N(E61) -> 3263.18 | G61: =IFERROR(LOOKUP(2^15,SEARCH('Category Rules'!$A$5:$A$23,C61),'Category Rules'!$B$5:$B$23),"Uncategorised") -> Income: client receipts | H61: =TEXT(B61,"mmm yyyy") -> Jul 2022
A62: =INDEX(Reconciliation!$A$6:$A$10,MATCH(B62,Reconciliation!$B$6:$B$10,1)) -> P2 | B62: 44744 | C62: Cash machine withdrawal on 30 Jun | D62: 102.37 | F62: =F61-N(D62)+N(E62) -> 3160.81 | G62: =IFERROR(LOOKUP(2^15,SEARCH('Category Rules'!$A$5:$A$23,C62),'Category Rules'!$B$5:$B$23),"Uncategorised") -> Cash withdrawals | H62: =TEXT(B62,"mmm yyyy") -> Jul 2022
A63: =INDEX(Reconciliation!$A$6:$A$10,MATCH(B63,Reconciliation!$B$6:$B$10,1)) -> P2 | B63: 44746 | C63: Internet banking transfer from savings account | E63: 200 | F63: =F62-N(D63)+N(E63) -> 3360.81 | G63: =IFERROR(LOOKUP(2^15,SEARCH('Category Rules'!$A$5:$A$23,C63),'Category Rules'!$B$5:$B$23),"Uncategorised") -> Income: transfers in | H63: =TEXT(B63,"mmm yyyy") -> Jul 2022
A64: =INDEX(Reconciliation!$A$6:$A$10,MATCH(B64,Reconciliation!$B$6:$B$10,1)) -> P2 | B64: 44746 | C64: Direct credit from Client B Ltd | E64: 195.49 | F64: =F63-N(D64)+N(E64) -> 3556.3 | G64: =IFERROR(LOOKUP(2^15,SEARCH('Category Rules'!$A$5:$A$23,C64),'Category Rules'!$B$5:$B$23),"Uncategorised") -> Income: client receipts | H64: =TEXT(B64,"mmm yyyy") -> Jul 2022
A65: =INDEX(Reconciliation!$A$6:$A$10,MATCH(B65,Reconciliation!$B$6:$B$10,1)) -> P2 | B65: 44746 | C65: Card payment to High Street Cafe on 04 Jul | D65: 6.51 | F65: =F64-N(D65)+N(E65) -> 3549.79 | G65: =IFERROR(LOOKUP(2^15,SEARCH('Category Rules'!$A$5:$A$23,C65),'Category Rules'!$B$5:$B$23),"Uncategorised") -> Meals and subsistence | H65: =TEXT(B65,"mmm yyyy") -> Jul 2022
A66: =INDEX(Reconciliation!$A$6:$A$10,MATCH(B66,Reconciliation!$B$6:$B$10,1)) -> P2 | B66: 44747 | C66: Internet banking transfer to savings account | D66: 1000 | F66: =F65-N(D66)+N(E66) -> 2549.79 | G66: =IFERROR(LOOKUP(2^15,SEARCH('Category Rules'!$A$5:$A$23,C66),'Category Rules'!$B$5:$B$23),"Uncategorised") -> Transfers out | H66: =TEXT(B66,"mmm yyyy") -> Jul 2022
A67: =INDEX(Reconciliation!$A$6:$A$10,MATCH(B67,Reconciliation!$B$6:$B$10,1)) -> P2 | B67: 44748 | C67: Card payment to Fuel Station 178 on 06 Jul | D67: 40.47 | F67: =F66-N(D67)+N(E67) -> 2509.32 | G67: =IFERROR(LOOKUP(2^15,SEARCH('Category Rules'!$A$5:$A$23,C67),'Category Rules'!$B$5:$B$23),"Uncategorised") -> Fuel and vehicle | H67: =TEXT(B67,"mmm yyyy") -> Jul 2022
A68: =INDEX(Reconciliation!$A$6:$A$10,MATCH(B68,Reconciliation!$B$6:$B$10,1)) -> P2 | B68: 44749 | C68: Card payment to Charity Shop 895 on 06 Jul | D68: 23.57 | F68: =F67-N(D68)+N(E68) -> 2485.75 | G68: =IFERROR(LOOKUP(2^15,SEARCH('Category Rules'!$A$5:$A$23,C68),'Category Rules'!$B$5:$B$23),"Uncategorised") -> Donations | H68: =TEXT(B68,"mmm yyyy") -> Jul 2022
A69: =INDEX(Reconciliation!$A$6:$A$10,MATCH(B69,Reconciliation!$B$6:$B$10,1)) -> P2 | B69: 44750 | C69: Commission charges for the period | D69: 8.5 | F69: =F68-N(D69)+N(E69) -> 2477.25 | G69: =IFERROR(LOOKUP(2^15,SEARCH('Category Rules'!$A$5:$A$23,C69),'Category Rules'!$B$5:$B$23),"Uncategorised") -> Bank charges | H69: =TEXT(B69,"mmm yyyy") -> Jul 2022
A70: =INDEX(Reconciliation!$A$6:$A$10,MATCH(B70,Reconciliation!$B$6:$B$10,1)) -> P2 | B70: 44752 | C70: Card payment to Fuel Station 282 on 08 Jul | D70: 73.23 | F70: =F69-N(D70)+N(E70) -> 2404.02 | G70: =IFERROR(LOOKUP(2^15,SEARCH('Category Rules'!$A$5:$A$23,C70),'Category Rules'!$B$5:$B$23),"Uncategorised") -> Fuel and vehicle | H70: =TEXT(B70,"mmm yyyy") -> Jul 2022
A71: =INDEX(Reconciliation!$A$6:$A$10,MATCH(B71,Reconciliation!$B$6:$B$10,1)) -> P2 | B71: 44752 | C71: Card payment to Cash and Carry 591 on 09 Jul | D71: 14.63 | F71: =F70-N(D71)+N(E71) -> 2389.39 | G71: =IFERROR(LOOKUP(2^15,SEARCH('Category Rules'!$A$5:$A$23,C71),'Category Rules'!$B$5:$B$23),"Uncategorised") -> Stock and supplies | H71: =TEXT(B71,"mmm yyyy") -> Jul 2022
A72: =INDEX(Reconciliation!$A$6:$A$10,MATCH(B72,Reconciliation!$B$6:$B$10,1)) -> P2 | B72: 44754 | C72: Internet banking transfer from savings account | E72: 150 | F72: =F71-N(D72)+N(E72) -> 2539.39 | G72: =IFERROR(LOOKUP(2^15,SEARCH('Category Rules'!$A$5:$A$23,C72),'Category Rules'!$B$5:$B$23),"Uncategorised") -> Income: transfers in | H72: =TEXT(B72,"mmm yyyy") -> Jul 2022
A73: =INDEX(Reconciliation!$A$6:$A$10,MATCH(B73,Reconciliation!$B$6:$B$10,1)) -> P2 | B73: 44755 | C73: Card payment to High Street Cafe on 13 Jul | D73: 5.01 | F73: =F72-N(D73)+N(E73) -> 2534.38 | G73: =IFERROR(LOOKUP(2^15,SEARCH('Category Rules'!$A$5:$A$23,C73),'Category Rules'!$B$5:$B$23),"Uncategorised") -> Meals and subsistence | H73: =TEXT(B73,"mmm yyyy") -> Jul 2022
A74: =INDEX(Reconciliation!$A$6:$A$10,MATCH(B74,Reconciliation!$B$6:$B$10,1)) -> P2 | B74: 44755 | C74: Card payment to Charity Shop 784 on 13 Jul | D74: 13.97 | F74: =F73-N(D74)+N(E74) -> 2520.41 | G74: =IFERROR(LOOKUP(2^15,SEARCH('Category Rules'!$A$5:$A$23,C74),'Category Rules'!$B$5:$B$23),"Uncategorised") -> Donations | H74: =TEXT(B74,"mmm yyyy") -> Jul 2022
A75: =INDEX(Reconciliation!$A$6:$A$10,MATCH(B75,Reconciliation!$B$6:$B$10,1)) -> P2 | B75: 44756 | C75: On line banking bill payment to Supplier A | D75: 25 | F75: =F74-N(D75)+N(E75) -> 2495.41 | G75: =IFERROR(LOOKUP(2^15,SEARCH('Category Rules'!$A$5:$A$23,C75),'Category Rules'!$B$5:$B$23),"Uncategorised") -> Supplier payments | H75: =TEXT(B75,"mmm yyyy") -> Jul 2022
A76: =INDEX(Reconciliation!$A$6:$A$10,MATCH(B76,Reconciliation!$B$6:$B$10,1)) -> P2 | B76: 44756 | C76: Card payment to Hardware Store on 12 Jul | D76: 66.04 | F76: =F75-N(D76)+N(E76) -> 2429.37 | G76: =IFERROR(LOOKUP(2^15,SEARCH('Category Rules'!$A$5:$A$23,C76),'Category Rules'!$B$5:$B$23),"Uncategorised") -> Office and equipment | H76: =TEXT(B76,"mmm yyyy") -> Jul 2022
A77: =INDEX(Reconciliation!$A$6:$A$10,MATCH(B77,Reconciliation!$B$6:$B$10,1)) -> P2 | B77: 44757 | C77: Card payment to Fuel Station 942 on 14 Jul | D77: 43.85 | F77: =F76-N(D77)+N(E77) -> 2385.52 | G77: =IFERROR(LOOKUP(2^15,SEARCH('Category Rules'!$A$5:$A$23,C77),'Category Rules'!$B$5:$B$23),"Uncategorised") -> Fuel and vehicle | H77: =TEXT(B77,"mmm yyyy") -> Jul 2022
A78: =INDEX(Reconciliation!$A$6:$A$10,MATCH(B78,Reconciliation!$B$6:$B$10,1)) -> P2 | B78: 44757 | C78: Card payment to Fuel Station 454 on 13 Jul | D78: 30.78 | F78: =F77-N(D78)+N(E78) -> 2354.74 | G78: =IFERROR(LOOKUP(2^15,SEARCH('Category Rules'!$A$5:$A$23,C78),'Category Rules'!$B$5:$B$23),"Uncategorised") -> Fuel and vehicle | H78: =TEXT(B78,"mmm yyyy") -> Jul 2022
A79: =INDEX(Reconciliation!$A$6:$A$10,MATCH(B79,Reconciliation!$B$6:$B$10,1)) -> P2 | B79: 44757 | C79: Card payment to Wholesale Club 797 on 14 Jul | D79: 152.5 | F79: =F78-N(D79)+N(E79) -> 2202.24 | G79: =IFERROR(LOOKUP(2^15,SEARCH('Category Rules'!$A$5:$A$23,C79),'Category Rules'!$B$5:$B$23),"Uncategorised") -> Stock and supplies | H79: =TEXT(B79,"mmm yyyy") -> Jul 2022
A80: =INDEX(Reconciliation!$A$6:$A$10,MATCH(B80,Reconciliation!$B$6:$B$10,1)) -> P2 | B80: 44757 | C80: Card payment to Cash and Carry 220 on 13 Jul | D80: 48.1 | F80: =F79-N(D80)+N(E80) -> 2154.14 | G80: =IFERROR(LOOKUP(2^15,SEARCH('Category Rules'!$A$5:$A$23,C80),'Category Rules'!$B$5:$B$23),"Uncategorised") -> Stock and supplies | H80: =TEXT(B80,"mmm yyyy") -> Jul 2022
A81: =INDEX(Reconciliation!$A$6:$A$10,MATCH(B81,Reconciliation!$B$6:$B$10,1)) -> P2 | B81: 44758 | C81: On line banking bill payment to Supplier A | D81: 250 | F81: =F80-N(D81)+N(E81) -> 1904.14 | G81: =IFERROR(LOOKUP(2^15,SEARCH('Category Rules'!$A$5:$A$23,C81),'Category Rules'!$B$5:$B$23),"Uncategorised") -> Supplier payments | H81: =TEXT(B81,"mmm yyyy") -> Jul 2022
A82: =INDEX(Reconciliation!$A$6:$A$10,MATCH(B82,Reconciliation!$B$6:$B$10,1)) -> P2 | B82: 44759 | C82: Card payment to Fuel Station 348 on 17 Jul | D82: 77.75 | F82: =F81-N(D82)+N(E82) -> 1826.39 | G82: =IFERROR(LOOKUP(2^15,SEARCH('Category Rules'!$A$5:$A$23,C82),'Category Rules'!$B$5:$B$23),"Uncategorised") -> Fuel and vehicle | H82: =TEXT(B82,"mmm yyyy") -> Jul 2022
A83: =INDEX(Reconciliation!$A$6:$A$10,MATCH(B83,Reconciliation!$B$6:$B$10,1)) -> P2 | B83: 44760 | C83: Card payment to Charity Shop 295 on 17 Jul | D83: 3.04 | F83: =F82-N(D83)+N(E83) -> 1823.35 | G83: =IFERROR(LOOKUP(2^15,SEARCH('Category Rules'!$A$5:$A$23,C83),'Category Rules'!$B$5:$B$23),"Uncategorised") -> Donations | H83: =TEXT(B83,"mmm yyyy") -> Jul 2022
A84: =INDEX(Reconciliation!$A$6:$A$10,MATCH(B84,Reconciliation!$B$6:$B$10,1)) -> P2 | B84: 44762 | C84: Card payment to Fuel Station 845 on 19 Jul | D84: 64.03 | F84: =F83-N(D84)+N(E84) -> 1759.32 | G84: =IFERROR(LOOKUP(2^15,SEARCH('Category Rules'!$A$5:$A$23,C84),'Category Rules'!$B$5:$B$23),"Uncategorised") -> Fuel and vehicle | H84: =TEXT(B84,"mmm yyyy") -> Jul 2022
... A86: =INDEX(Reconciliation!$A$6:$A$10,MATCH(B86,Reconciliation!$B$6:$B$10,1)) -> P2 | B86: 44763 | C86: Card payment to Corner Grocer on 19 Jul | D86: 9.74 | F86: =F85-N(D86)+N(E86) -> 1672.82 | G86: =IFERROR(LOOKUP(2^15,SEARCH('Category Rules'!$A$5:$A$23,C86),'Category Rules'!$B$5:$B$23),"Uncategorised") -> Stock and supplies | H86: =TEXT(B86,"mmm yyyy") -> Jul 2022
A87: =INDEX(Reconciliation!$A$6:$A$10,MATCH(B87,Reconciliation!$B$6:$B$10,1)) -> P2 | B87: 44764 | C87: Direct credit from Client B Ltd | E87: 106.72 | F87: =F86-N(D87)+N(E87) -> 1779.54 | G87: =IFERROR(LOOKUP(2^15,SEARCH('Category Rules'!$A$5:$A$23,C87),'Category Rules'!$B$5:$B$23),"Uncategorised") -> Income: client receipts | H87: =TEXT(B87,"mmm yyyy") -> Jul 2022
A88: =INDEX(Reconciliation!$A$6:$A$10,MATCH(B88,Reconciliation!$B$6:$B$10,1)) -> P3 | B88: 44765 | C88: On line banking bill payment to Supplier A | D88: 1000 | F88: =F87-N(D88)+N(E88) -> 779.54 | G88: =IFERROR(LOOKUP(2^15,SEARCH('Category Rules'!$A$5:$A$23,C88),'Category Rules'!$B$5:$B$23),"Uncategorised") -> Supplier payments | H88: =TEXT(B88,"mmm yyyy") -> Jul 2022
A89: =INDEX(Reconciliation!$A$6:$A$10,MATCH(B89,Reconciliation!$B$6:$B$10,1)) -> P3 | B89: 44766 | C89: Card payment to High Street Cafe on 22 Jul | D89: 7.25 | F89: =F88-N(D89)+N(E89) -> 772.29 | G89: =IFERROR(LOOKUP(2^15,SEARCH('Category Rules'!$A$5:$A$23,C89),'Category Rules'!$B$5:$B$23),"Uncategorised") -> Meals and subsistence | H89: =TEXT(B89,"mmm yyyy") -> Jul 2022
A90: =INDEX(Reconciliation!$A$6:$A$10,MATCH(B90,Reconciliation!$B$6:$B$10,1)) -> P3 | B90: 44766 | C90: Card payment to Cash and Carry 731 on 22 Jul | D90: 37.41 | F90: =F89-N(D90)+N(E90) -> 734.88 | G90: =IFERROR(LOOKUP(2^15,SEARCH('Category Rules'!$A$5:$A$23,C90),'Category Rules'!$B$5:$B$23),"Uncategorised") -> Stock and supplies | H90: =TEXT(B90,"mmm yyyy") -> Jul 2022
A91: =INDEX(Reconciliation!$A$6:$A$10,MATCH(B91,Reconciliation!$B$6:$B$10,1)) -> P3 | B91: 44766 | C91: Card payment to Wholesale Club 133 on 22 Jul | D91: 221.02 | F91: =F90-N(D91)+N(E91) -> 513.86 | G91: =IFERROR(LOOKUP(2^15,SEARCH('Category Rules'!$A$5:$A$23,C91),'Category Rules'!$B$5:$B$23),"Uncategorised") -> Stock and supplies | H91: =TEXT(B91,"mmm yyyy") -> Jul 2022
A92: =INDEX(Reconciliation!$A$6:$A$10,MATCH(B92,Reconciliation!$B$6:$B$10,1)) -> P3 | B92: 44768 | C92: Direct credit from Client C Ltd | E92: 1018.21 | F92: =F91-N(D92)+N(E92) -> 1532.07 | G92: =IFERROR(LOOKUP(2^15,SEARCH('Category Rules'!$A$5:$A$23,C92),'Category Rules'!$B$5:$B$23),"Uncategorised") -> Income: client receipts | H92: =TEXT(B92,"mmm yyyy") -> Jul 2022
A93: =INDEX(Reconciliation!$A$6:$A$10,MATCH(B93,Reconciliation!$B$6:$B$10,1)) -> P3 | B93: 44769 | C93: Cash machine withdrawal on 25 Jul | D93: 115.6 | F93: =F92-N(D93)+N(E93) -> 1416.47 | G93: =IFERROR(LOOKUP(2^15,SEARCH('Category Rules'!$A$5:$A$23,C93),'Category Rules'!$B$5:$B$23),"Uncategorised") -> Cash withdrawals | H93: =TEXT(B93,"mmm yyyy") -> Jul 2022
A94: =INDEX(Reconciliation!$A$6:$A$10,MATCH(B94,Reconciliation!$B$6:$B$10,1)) -> P3 | B94: 44769 | C94: Card payment to Garage Services on 25 Jul | D94: 62.97 | F94: =F93-N(D94)+N(E94) -> 1353.5 | G94: =IFERROR(LOOKUP(2^15,SEARCH('Category Rules'!$A$5:$A$23,C94),'Category Rules'!$B$5:$B$23),"Uncategorised") -> Fuel and vehicle | H94: =TEXT(B94,"mmm yyyy") -> Jul 2022
A95: =INDEX(Reconciliation!$A$6:$A$10,MATCH(B95,Reconciliation!$B$6:$B$10,1)) -> P3 | B95: 44770 | C95: Direct credit from Client B Ltd | E95: 170.14 | F95: =F94-N(D95)+N(E95) -> 1523.64 | G95: =IFERROR(LOOKUP(2^15,SEARCH('Category Rules'!$A$5:$A$23,C95),'Category Rules'!$B$5:$B$23),"Uncategorised") -> Income: client receipts | H95: =TEXT(B95,"mmm yyyy") -> Jul 2022
A96: =INDEX(Reconciliation!$A$6:$A$10,MATCH(B96,Reconciliation!$B$6:$B$10,1)) -> P3 | B96: 44771 | C96: Internet banking transfer from savings account | E96: 250 | F96: =F95-N(D96)+N(E96) -> 1773.64 | G96: =IFERROR(LOOKUP(2^15,SEARCH('Category Rules'!$A$5:$A$23,C96),'Category Rules'!$B$5:$B$23),"Uncategorised") -> Income: transfers in | H96: =TEXT(B96,"mmm yyyy") -> Jul 2022
A97: =INDEX(Reconciliation!$A$6:$A$10,MATCH(B97,Reconciliation!$B$6:$B$10,1)) -> P3 | B97: 44771 | C97: Card payment to Cash and Carry 196 on 29 Jul | D97: 56.88 | F97: =F96-N(D97)+N(E97) -> 1716.76 | G97: =IFERROR(LOOKUP(2^15,SEARCH('Category Rules'!$A$5:$A$23,C97),'Category Rules'!$B$5:$B$23),"Uncategorised") -> Stock and supplies | H97: =TEXT(B97,"mmm yyyy") -> Jul 2022
A98: =INDEX(Reconciliation!$A$6:$A$10,MATCH(B98,Reconciliation!$B$6:$B$10,1)) -> P3 | B98: 44773 | C98: Card payment to Wholesale Club 912 on 29 Jul | D98: 223.91 | F98: =F97-N(D98)+N(E98) -> 1492.85 | G98: =IFERROR(LOOKUP(2^15,SEARCH('Category Rules'!$A$5:$A$23,C98),'Category Rules'!$B$5:$B$23),"Uncategorised") -> Stock and supplies | H98: =TEXT(B98,"mmm yyyy") -> Jul 2022
A99: =INDEX(Reconciliation!$A$6:$A$10,MATCH(B99,Reconciliation!$B$6:$B$10,1)) -> P3 | B99: 44773 | C99: Card payment to Cash and Carry 189 on 31 Jul | D99: 55.19 | F99: =F98-N(D99)+N(E99) -> 1437.66 | G99: =IFERROR(LOOKUP(2^15,SEARCH('Category Rules'!$A$5:$A$23,C99),'Category Rules'!$B$5:$B$23),"Uncategorised") -> Stock and supplies | H99: =TEXT(B99,"mmm yyyy") -> Jul 2022
A100: =INDEX(Reconciliation!$A$6:$A$10,MATCH(B100,Reconciliation!$B$6:$B$10,1)) -> P3 | B100: 44773 | C100: Card payment to Cash and Carry 851 on 30 Jul | D100: 6.17 | F100: =F99-N(D100)+N(E100) -> 1431.49 | G100: =IFERROR(LOOKUP(2^15,SEARCH('Category Rules'!$A$5:$A$23,C100),'Category Rules'!$B$5:$B$23),"Uncategorised") -> Stock and supplies | H100: =TEXT(B100,"mmm yyyy") -> Jul 2022
A101: =INDEX(Reconciliation!$A$6:$A$10,MATCH(B101,Reconciliation!$B$6:$B$10,1)) -> P3 | B101: 44774 | C101: Direct debit to Telecom Co | D101: 8.2 | F101: =F100-N(D101)+N(E101) -> 1423.29 | G101: =IFERROR(LOOKUP(2^15,SEARCH('Category Rules'!$A$5:$A$23,C101),'Category Rules'!$B$5:$B$23),"Uncategorised") -> Subscriptions and utilities | H101: =TEXT(B101,"mmm yyyy") -> Aug 2022
A102: =INDEX(Reconciliation!$A$6:$A$10,MATCH(B102,Reconciliation!$B$6:$B$10,1)) -> P3 | B102: 44776 | C102: Internet banking transfer to savings account | D102: 500 | F102: =F101-N(D102)+N(E102) -> 923.29 | G102: =IFERROR(LOOKUP(2^15,SEARCH('Category Rules'!$A$5:$A$23,C102),'Category Rules'!$B$5:$B$23),"Uncategorised") -> Transfers out | H102: =TEXT(B102,"mmm yyyy") -> Aug 2022
...

Sheet Reconciliation
A1: Statement reconciliation
A2: Each period's computed closing balance must equal the balance printed on the statement.
A5: Period | B5: From | C5: To | D5: Opening balance (£) | E5: Money out (£) | F5: Money in (£) | G5: Computed closing (£) | H5: Statement closing (£) | I5: Difference (£) | J5: Status | K5: Transactions
A6: P1 | B6: 44702 | C6: 44734 | D6: =Transactions!$D$3 -> 2410 | E6: =SUMIFS(Transactions!$D$6:$D$188,Transactions!$A$6:$A$188,A6) -> 2038.68 | F6: =SUMIFS(Transactions!$E$6:$E$188,Transactions!$A$6:$A$188,A6) -> 2626.21 | G6: =D6-E6+F6 -> 2997.53 | H6: 2997.53 | I6: =ROUND(G6-H6,2) -> 0 | J6: =IF(I6=0,"Reconciled","Check") -> Reconciled | K6: =COUNTIF(Transactions!$A$6:$A$188,A6) -> 44
A7: P2 | B7: 44735 | C7: 44764 | D7: =H6 -> 2997.53 | E7: =SUMIFS(Transactions!$D$6:$D$188,Transactions!$A$6:$A$188,A7) -> 2741.44 | F7: =SUMIFS(Transactions!$E$6:$E$188,Transactions!$A$6:$A$188,A7) -> 1523.45 | G7: =D7-E7+F7 -> 1779.54 | H7: 1779.54 | I7: =ROUND(G7-H7,2) -> 0 | J7: =IF(I7=0,"Reconciled","Check") -> Reconciled | K7: =COUNTIF(Transactions!$A$6:$A$188,A7) -> 38
A8: P3 | B8: 44765 | C8: 44795 | D8: =H7 -> 1779.54 | E8: =SUMIFS(Transactions!$D$6:$D$188,Transactions!$A$6:$A$188,A8) -> 3841.47 | F8: =SUMIFS(Transactions!$E$6:$E$188,Transactions!$A$6:$A$188,A8) -> 4755 | G8: =D8-E8+F8 -> 2693.07 | H8: 2693.07 | I8: =ROUND(G8-H8,2) -> 0 | J8: =IF(I8=0,"Reconciled","Check") -> Reconciled | K8: =COUNTIF(Transactions!$A$6:$A$188,A8) -> 40
A9: P4 | B9: 44796 | C9: 44826 | D9: =H8 -> 2693.07 | E9: =SUMIFS(Transactions!$D$6:$D$188,Transactions!$A$6:$A$188,A9) -> 3443.76 | F9: =SUMIFS(Transactions!$E$6:$E$188,Transactions!$A$6:$A$188,A9) -> 2757.71 | G9: =D9-E9+F9 -> 2007.02 | H9: 2007.02 | I9: =ROUND(G9-H9,2) -> 0 | J9: =IF(I9=0,"Reconciled","Check") -> Reconciled | K9: =COUNTIF(Transactions!$A$6:$A$188,A9) -> 39
A10: P5 | B10: 44827 | C10: 44845 | D10: =H9 -> 2007.02 | E10: =SUMIFS(Transactions!$D$6:$D$188,Transactions!$A$6:$A$188,A10) -> 937.42 | F10: =SUMIFS(Transactions!$E$6:$E$188,Transactions!$A$6:$A$188,A10) -> 445.88 | G10: =D10-E10+F10 -> 1515.48 | H10: 1515.48 | I10: =ROUND(G10-H10,2) -> 0 | J10: =IF(I10=0,"Reconciled","Check") -> Reconciled | K10: =COUNTIF(Transactions!$A$6:$A$188,A10) -> 22
A11: Total | E11: =SUM(E6:E10) -> 13002.77 | F11: =SUM(F6:F10) -> 12108.25 | K11: =SUM(K6:K10) -> 183
A13: The statement closing balances are typed from each printed statement. Statement 5 is the final statement for the account.

Sheet Category Rules
A1: Category rules
A2: Keyword found anywhere in the description sets the category. Keep keywords specific.
A4: Keyword | B4: Category | C4: Direction
A5: Direct credit | B5: Income: client receipts | C5: in
A6: Transfer from | B6: Income: transfers in | C6: in
A7: Transfer to | B7: Transfers out | C7: out
A8: Bill payment | B8: Supplier payments | C8: out
A9: Fuel | B9: Fuel and vehicle | C9: out
A10: Garage | B10: Fuel and vehicle | C10: out
A11: Tyre | B11: Fuel and vehicle | C11: out
A12: Wholesale | B12: Stock and supplies | C12: out
A13: Cash and carry | B13: Stock and supplies | C13: out
A14: Grocer | B14: Stock and supplies | C14: out
A15: Cash machine | B15: Cash withdrawals | C15: out
... A23: Hardware | B23: Office and equipment | C23: out

Sheet Checks
A1: Checks
A2: Every line should read OK before the budget is used.
A4: Check | B4: Value | C4: Expected | D4: Result
A5: Transactions in the ledger | B5: =COUNTA(Transactions!$C$6:$C$188) -> 183 | C5: 183 | D5: =IF(B5=C5,"OK","CHECK") -> OK
A6: Uncategorised transactions | B6: =COUNTIF(Transactions!$G$6:$G$188,"Uncategorised") -> 0 | C6: 0 | D6: =IF(B6=C6,"OK","CHECK") -> OK
A7: Periods reconciled to the statement | B7: =COUNTIF(Reconciliation!$J$6:$J$10,"Reconciled") -> 5 | C7: 5 | D7: =IF(B7=C7,"OK","CHECK") -> OK
A8: Ledger money out less budget spending total | B8: =ROUND(SUM(Transactions!$D$6:$D$188)-Budget!G20,2) -> 0 | C8: 0 | D8: =IF(B8=C8,"OK","CHECK") -> OK
A9: Ledger money in less budget income total | B9: =ROUND(SUM(Transactions!$E$6:$E$188)-Budget!G25,2) -> 0 | C9: 0 | D9: =IF(B9=C9,"OK","CHECK") -> OK
A10: Final running balance less statement 5 closing | B10: =ROUND(Transactions!F188-Reconciliation!H10,2) -> 0 | C10: 0 | D10: =IF(B10=C10,"OK","CHECK") -> OK
